<?xml version="1.0" encoding="utf-8" ?>
<ZetboxConfig xmlns="http://dasz.at/Zetbox/">
  <ConfigName>CI Server Configuration</ConfigName>
  <Server StartServer="true">
    <DocumentStore>..\DocumentStore\Server/</DocumentStore>
    <CodeGenWorkingPath>..\bin\CodeGenNext</CodeGenWorkingPath>
    <CodeGenOutputPath>..\bin\CodeGen</CodeGenOutputPath>
    <CodeGenBinaryOutputPath>
      <string>.\</string>
    </CodeGenBinaryOutputPath>
    <CodeGenArchivePath>..\Backup</CodeGenArchivePath>
    <Modules>
      <Module>Zetbox.Server.UnifiedModule, Zetbox.Server</Module>

      <Module>Zetbox.Objects.EfModule, Zetbox.Objects.EfImpl</Module>
      <Module>Zetbox.DalProvider.Ef.EfProvider, Zetbox.DalProvider.Ef</Module>

      <Module>Zetbox.App.Projekte.Server.CustomServerActionsModule, Zetbox.App.Projekte.Server</Module>
      <Module>Zetbox.App.Projekte.Common.CustomCommonActionsModule, Zetbox.App.Projekte.Common</Module>

      <!-- Development/Master Server modules -->
      <Module>Zetbox.Generator.GeneratorModule, Zetbox.Generator</Module>
      <Module>Zetbox.DalProvider.Memory.Generator.MemoryGeneratorProvider, Zetbox.DalProvider.Memory.Generator</Module>
      <Module>Zetbox.DalProvider.Client.Generator.ClientGeneratorProvider, Zetbox.DalProvider.Client.Generator</Module>
      <Module>Zetbox.DalProvider.Ef.Generator.EfGeneratorProvider, Zetbox.DalProvider.Ef.Generator</Module>
    </Modules>
  </Server>
  <AssemblySearchPaths>
    <string>Common\Core</string>
    <string>Common\Core.Generated</string>
    <string>Common\Core.Fallback</string>
    <string>Server\Core</string>
    <string>Server\EF</string>
    <string>Server\EF.Generated</string>
    <string>Server\EF.Fallback</string>
    <string>Common\App.Zetbox</string>
    <string>Server\App.Zetbox</string>
  </AssemblySearchPaths>
</ZetboxConfig>
